grpc_nacos/__init__.py
grpc_nacos/v1/__init__.py
grpc_nacos/v1/aio_channel.py
grpc_nacos/v1/channel.py
grpc_nacos/v1/client.py
grpc_nacos/v1/internals/__init__.py
grpc_nacos/v1/internals/auth.py
grpc_nacos/v1/internals/client.py
grpc_nacos/v1/internals/commons.py
grpc_nacos/v1/internals/exception.py
grpc_nacos/v1/internals/files.py
grpc_nacos/v1/internals/listener.py
grpc_nacos/v1/internals/params.py
grpc_nacos/v1/internals/task.py
grpc_nacos/v1/internals/timer.py
grpc_nacos/v1/models.py
grpc_nacos/v1/service_info_cache.py
grpc_nacos/v1/utils.py
grpc_nacos/v2/__init__.py
grpc_nacos/v2/channel.py
grpc_nacos/v2/client.py
grpc_nacos/v2/internals/__init__.py
grpc_nacos/v2/internals/common/__init__.py
grpc_nacos/v2/internals/common/auth.py
grpc_nacos/v2/internals/common/client_config.py
grpc_nacos/v2/internals/common/client_config_builder.py
grpc_nacos/v2/internals/common/constants.py
grpc_nacos/v2/internals/common/nacos_exception.py
grpc_nacos/v2/internals/common/payload_registry.py
grpc_nacos/v2/internals/common/preserved_metadata_key.py
grpc_nacos/v2/internals/config/__init__.py
grpc_nacos/v2/internals/config/cache/__init__.py
grpc_nacos/v2/internals/config/cache/config_info_cache.py
grpc_nacos/v2/internals/config/cache/config_subscribe_manager.py
grpc_nacos/v2/internals/config/filter/__init__.py
grpc_nacos/v2/internals/config/filter/config_filter.py
grpc_nacos/v2/internals/config/model/__init__.py
grpc_nacos/v2/internals/config/model/config.py
grpc_nacos/v2/internals/config/model/config_param.py
grpc_nacos/v2/internals/config/model/config_request.py
grpc_nacos/v2/internals/config/model/config_response.py
grpc_nacos/v2/internals/config/nacos_config_service.py
grpc_nacos/v2/internals/config/remote/__init__.py
grpc_nacos/v2/internals/config/remote/config_change_notify_request_handler.py
grpc_nacos/v2/internals/config/remote/config_grpc_client_proxy.py
grpc_nacos/v2/internals/config/remote/config_grpc_connection_event_listener.py
grpc_nacos-0.0.4.dist-info/WHEEL
grpc_nacos-0.0.4.dist-info/METADATA
grpc_nacos-0.0.4.dist-info/RECORD
