Metadata-Version: 2.3
Name: grpc-nacos
Version: 0.0.4
Summary: This lib provides a gRPC client combined with Nacos service discovery.
Author: Richard Yang
Author-email: Richard Yang <zhongtian.yang@qq.com>
License: MIT
Requires-Dist: aiofiles>=24.1.0
Requires-Dist: aiohttp>=3.10.11
Requires-Dist: grpcio>=1.66.1
Requires-Dist: pydantic>=2.0.0
Requires-Dist: pycryptodome>=3.19.1
Requires-Dist: psutil>=5.9.5
Maintainer: Richard Yang
Maintainer-email: Richard Yang <zhongtian.yang@qq.com>
Requires-Python: >=3.10
